scripts/__init__.py
scripts/check_env.py
scripts/preprocess_cli.py
scripts/train_zachvit_cli.py
zachvit/__init__.py
zachvit/constants.py
zachvit/model_utils.py
zachvit/preprocessing_utils.py
zachvit/zachvit_model_utils.py
zachvit-1.0.0.dist-info/licenses/LICENSE
zachvit-1.0.0.dist-info/METADATA
zachvit-1.0.0.dist-info/WHEEL
zachvit-1.0.0.dist-info/entry_points.txt
zachvit-1.0.0.dist-info/top_level.txt
zachvit-1.0.0.dist-info/RECORD
