Metadata-Version: 2.4
Name: zachvit
Version: 1.0.0
Summary: Official implementation of ZACH-ViT: Zero-Token Adaptive Compact Hierarchical Vision Transformer with ShuffleStrides Data Augmentation (SSDA).
Home-page: https://github.com/Bluesman79/ZACH-ViT
Author: Athanasios Angelakis
Author-email: angelakis.athanasios@gmail.com
License: Apache-2.0
Project-URL: Paper, https://arxiv.org/abs/2510.17650
Project-URL: DOI, https://doi.org/10.48550/arXiv.2510.17650
Keywords: vision transformer,medical imaging,ultrasound,explainable AI,deep learning,lung ultrasound,computer vision
Classifier: Programming Language :: Python :: 3
Classifier: License :: OSI Approved :: Apache Software License
Classifier: Operating System :: OS Independent
Classifier: Topic :: Scientific/Engineering :: Artificial Intelligence
Classifier: Topic :: Scientific/Engineering :: Medical Science Apps.
Classifier: Intended Audience :: Science/Research
Requires-Python: >=3.10
License-File: LICENSE
Requires-Dist: tensorflow==2.19.0
Requires-Dist: keras==3.5.0
Requires-Dist: numpy==1.26.4
Requires-Dist: pandas==2.3.2
Requires-Dist: matplotlib==3.10.5
Requires-Dist: pydicom==3.0.1
Requires-Dist: scikit-image==0.20.0
Requires-Dist: Pillow==11.3.0
Requires-Dist: scikit-learn==1.7.1
Requires-Dist: IPython==8.20.0
Dynamic: author
Dynamic: author-email
Dynamic: classifier
Dynamic: description
Dynamic: description-content-type
Dynamic: home-page
Dynamic: keywords
Dynamic: license
Dynamic: license-file
Dynamic: project-url
Dynamic: requires-dist
Dynamic: requires-python
Dynamic: summary
